TSDetective/__init__.py
TSDetective/method.py
TSDetective-0.0.1.dist-info/LICENSE
TSDetective-0.0.1.dist-info/METADATA
TSDetective-0.0.1.dist-info/WHEEL
TSDetective-0.0.1.dist-info/top_level.txt
TSDetective-0.0.1.dist-info/RECORD
